jupyterlab_classic/__init__.py
jupyterlab_classic/__main__.py
jupyterlab_classic/_version.py
jupyterlab_classic/app.py
jupyterlab_classic/serverextension.py
jupyterlab_classic/labextension/build_log.json
jupyterlab_classic/labextension/package.json
jupyterlab_classic/labextension/static/lib_index_js.090562931dddacf6a920.js
jupyterlab_classic/labextension/static/lib_index_js.090562931dddacf6a920.js.map
jupyterlab_classic/labextension/static/remoteEntry.ac00b968961d58dbf324.js
jupyterlab_classic/labextension/static/remoteEntry.ac00b968961d58dbf324.js.map
jupyterlab_classic/labextension/static/style.js
jupyterlab_classic/labextension/static/style_index_js.bd2230bdd8d633df32f0.js
jupyterlab_classic/labextension/static/style_index_js.bd2230bdd8d633df32f0.js.map
jupyterlab_classic/labextension/static/vendors-node_modules_css-loader_dist_runtime_api_js-node_modules_css-loader_dist_runtime_cssW-926fd9.94a9b28c487af6cd4aee.js
jupyterlab_classic/labextension/static/vendors-node_modules_css-loader_dist_runtime_api_js-node_modules_css-loader_dist_runtime_cssW-926fd9.94a9b28c487af6cd4aee.js.map
jupyterlab_classic/static/099a9556e1a63ece24f8a99859c94c7d.woff
jupyterlab_classic/static/1036.bundle.js
jupyterlab_classic/static/1042e8ca1ce821518a2d3e7055410839.eot
jupyterlab_classic/static/1057.bundle.js
jupyterlab_classic/static/1058.bundle.js
jupyterlab_classic/static/1124.bundle.js
jupyterlab_classic/static/1159.bundle.js
jupyterlab_classic/static/1289.bundle.js
jupyterlab_classic/static/1289.bundle.js.LICENSE.txt
jupyterlab_classic/static/1336.bundle.js
jupyterlab_classic/static/1337.bundle.js
jupyterlab_classic/static/1356.bundle.js
jupyterlab_classic/static/1382.bundle.js
jupyterlab_classic/static/13de59f1a36b6cb4bca0050160ff0e41.svg
jupyterlab_classic/static/1492.bundle.js
jupyterlab_classic/static/1492.bundle.js.LICENSE.txt
jupyterlab_classic/static/1542.bundle.js
jupyterlab_classic/static/1542.bundle.js.LICENSE.txt
jupyterlab_classic/static/1619.bundle.js
jupyterlab_classic-0.1.11.dist-info/LICENSE
jupyterlab_classic-0.1.11.dist-info/METADATA
jupyterlab_classic-0.1.11.dist-info/WHEEL
jupyterlab_classic-0.1.11.dist-info/entry_points.txt
jupyterlab_classic-0.1.11.dist-info/top_level.txt
jupyterlab_classic-0.1.11.dist-info/RECORD
