Metadata-Version: 2.1
Name: jupyterlab-classic
Version: 0.1.11
Summary: The next gen old-school Notebook UI
Home-page: https://github.com/jtpio/jupyterlab-classic
Author: JupyterLab Classic Contributors
License: BSD-3-Clause
Keywords: Jupyter,JupyterLab,Notebook
Platform: Linux
Platform: Mac OS X
Platform: Windows
Classifier: License :: OSI Approved :: BSD License
Classifier: Programming Language :: Python
Classifier: Programming Language :: Python :: 3
Classifier: Programming Language :: Python :: 3.6
Classifier: Programming Language :: Python :: 3.7
Classifier: Programming Language :: Python :: 3.8
Classifier: Programming Language :: Python :: 3.9
Classifier: Framework :: Jupyter
Requires-Python: >=3.6
License-File: LICENSE
Requires-Dist: jupyterlab (<4,>=3.0.9)
Requires-Dist: jupyterlab-server (~=2.3)
Requires-Dist: jupyter-server (~=1.4)
Requires-Dist: nbclassic (~=0.2)
Requires-Dist: tornado (>=6.1.0)
